{
  "content": [
    {
      "content": null,
      "created": "2024-09-23T00:43:41.493909Z",
      "format": null,
      "last_modified": "2024-09-23T00:43:21.181767Z",
      "mimetype": null,
      "name": "data-science-python-exceptions.ipynb",
      "path": "data-science-python-exceptions.ipynb",
      "size": 12059,
      "type": "notebook",
      "writable": true
    },
    {
      "content": null,
      "created": "2024-09-23T00:43:41.495908Z",
      "format": null,
      "last_modified": "2024-09-23T00:43:21.190768Z",
      "mimetype": null,
      "name": "data-science-python-iterables.ipynb",
      "path": "data-science-python-iterables.ipynb",
      "size": 68475,
      "type": "notebook",
      "writable": true
    },
    {
      "content": null,
      "created": "2024-09-23T00:43:41.495908Z",
      "format": null,
      "last_modified": "2024-09-23T00:43:21.193768Z",
      "mimetype": null,
      "name": "data-science-python-math.ipynb",
      "path": "data-science-python-math.ipynb",
      "size": 28206,
      "type": "notebook",
      "writable": true
    },
    {
      "content": null,
      "created": "2024-09-23T00:43:41.496909Z",
      "format": null,
      "last_modified": "2024-09-23T00:43:21.196768Z",
      "mimetype": null,
      "name": "data-science-python-plotting.ipynb",
      "path": "data-science-python-plotting.ipynb",
      "size": 141711,
      "type": "notebook",
      "writable": true
    },
    {
      "content": null,
      "created": "2024-09-23T00:43:41.498909Z",
      "format": null,
      "last_modified": "2024-09-23T00:43:21.200768Z",
      "mimetype": null,
      "name": "data-science-python-types.ipynb",
      "path": "data-science-python-types.ipynb",
      "size": 29250,
      "type": "notebook",
      "writable": true
    },
    {
      "content": null,
      "created": "2024-09-23T00:43:41.494909Z",
      "format": null,
      "last_modified": "2024-09-23T00:43:21.187768Z",
      "mimetype": null,
      "name": "data-science-python-functions.ipynb",
      "path": "data-science-python-functions.ipynb",
      "size": 37212,
      "type": "notebook",
      "writable": true
    },
    {
      "content": null,
      "created": "2024-09-23T00:43:41.491909Z",
      "format": null,
      "last_modified": "2024-09-23T00:43:21.176767Z",
      "mimetype": null,
      "name": "data-science-python-advanced-np-pd.ipynb",
      "path": "data-science-python-advanced-np-pd.ipynb",
      "size": 114653,
      "type": "notebook",
      "writable": true
    },
    {
      "content": null,
      "created": "2024-09-23T00:43:41.495908Z",
      "format": null,
      "last_modified": "2024-09-23T00:43:21.191767Z",
      "mimetype": null,
      "name": "data-science-python-loops.ipynb",
      "path": "data-science-python-loops.ipynb",
      "size": 45142,
      "type": "notebook",
      "writable": true
    },
    {
      "content": null,
      "created": "2024-09-23T00:43:41.497909Z",
      "format": null,
      "last_modified": "2024-09-23T00:43:21.197767Z",
      "mimetype": null,
      "name": "data-science-python-subprocess.ipynb",
      "path": "data-science-python-subprocess.ipynb",
      "size": 23107,
      "type": "notebook",
      "writable": true
    },
    {
      "content": null,
      "created": "2024-09-23T00:43:41.498909Z",
      "format": null,
      "last_modified": "2024-09-23T00:43:21.202768Z",
      "mimetype": null,
      "name": "data-science-python-typing.ipynb",
      "path": "data-science-python-typing.ipynb",
      "size": 134862,
      "type": "notebook",
      "writable": true
    },
    {
      "content": null,
      "created": "2024-09-23T00:43:41.492908Z",
      "format": null,
      "last_modified": "2024-09-23T00:43:21.178767Z",
      "mimetype": null,
      "name": "data-science-python-basics.ipynb",
      "path": "data-science-python-basics.ipynb",
      "size": 159588,
      "type": "notebook",
      "writable": true
    },
    {
      "content": null,
      "created": "2024-09-23T00:43:41.493909Z",
      "format": null,
      "last_modified": "2024-09-23T00:43:21.183768Z",
      "mimetype": null,
      "name": "data-science-python-files.ipynb",
      "path": "data-science-python-files.ipynb",
      "size": 43044,
      "type": "notebook",
      "writable": true
    },
    {
      "content": null,
      "created": "2024-09-23T00:43:41.496909Z",
      "format": null,
      "last_modified": "2024-09-23T00:43:21.194767Z",
      "mimetype": null,
      "name": "data-science-python-multiprocessing.ipynb",
      "path": "data-science-python-multiprocessing.ipynb",
      "size": 44276,
      "type": "notebook",
      "writable": true
    },
    {
      "content": null,
      "created": "2024-09-23T00:43:41.497909Z",
      "format": null,
      "last_modified": "2024-09-23T00:43:21.199768Z",
      "mimetype": null,
      "name": "data-science-python-testing.ipynb",
      "path": "data-science-python-testing.ipynb",
      "size": 22271,
      "type": "notebook",
      "writable": true
    },
    {
      "content": null,
      "created": "2024-09-23T00:43:41.493909Z",
      "format": null,
      "last_modified": "2024-09-23T00:43:21.185767Z",
      "mimetype": null,
      "name": "data-science-python-flow.ipynb",
      "path": "data-science-python-flow.ipynb",
      "size": 42807,
      "type": "notebook",
      "writable": true
    },
    {
      "content": null,
      "created": "2024-09-23T00:43:41.491909Z",
      "format": null,
      "last_modified": "2024-09-23T00:43:21.180768Z",
      "mimetype": null,
      "name": "data-science-python-basics-recap.ipynb",
      "path": "data-science-python-basics-recap.ipynb",
      "size": 30699,
      "type": "notebook",
      "writable": true
    },
    {
      "content": null,
      "created": "2024-09-23T00:43:41.494909Z",
      "format": null,
      "last_modified": "2024-09-23T00:43:21.188767Z",
      "mimetype": null,
      "name": "data-science-python-glob.ipynb",
      "path": "data-science-python-glob.ipynb",
      "size": 9468,
      "type": "notebook",
      "writable": true
    }
  ],
  "created": "2024-09-23T00:43:41.498909Z",
  "format": "json",
  "last_modified": "2024-09-23T00:43:41.498909Z",
  "mimetype": null,
  "name": "",
  "path": "",
  "size": null,
  "type": "directory",
  "writable": true
}